{
  "actualizado": "2026-07-20 19:18",
  "totalPlantas": 17,
  "plantas": [
    {
      "id": 53013,
      "nombre": "Federico Paulini",
      "kwp": 6.6,
      "tipo": "BATTERY_BACKUP",
      "estado": "NORMAL",
      "potenciaActual": 579.0,
      "consumoActual": 813.0,
      "bateriaSOC": 49.0,
      "dia": {
        "generation": 4.9,
        "consumption": 10.8,
        "grid": 0.0,
        "purchase": 5.0,
        "charge": 2.2,
        "discharge": 3.1
      },
      "mes": {
        "generation": 215.8,
        "consumption": 381.4,
        "grid": 0.7,
        "purchase": 167.0,
        "charge": 106.3,
        "discharge": 105.6
      },
      "anio": {
        "generation": 4207.8,
        "consumption": 7537.6,
        "grid": 11.1,
        "purchase": 3455.5,
        "charge": 1632.0,
        "discharge": 1517.4
      },
      "alertas3d": 0,
      "alertaPrincipal": ""
    },
    {
      "id": 53071,
      "nombre": "Facundo Cativiela",
      "kwp": 5.5,
      "tipo": "BATTERY_BACKUP",
      "estado": "NORMAL",
      "potenciaActual": 174.0,
      "consumoActual": 207.0,
      "bateriaSOC": 45.0,
      "dia": {
        "generation": 2.1,
        "consumption": 6.0,
        "grid": 0.0,
        "purchase": 4.7,
        "charge": 0.9,
        "discharge": 0.1
      },
      "mes": {
        "generation": 106.2,
        "consumption": 407.0,
        "grid": 0.0,
        "purchase": 310.3,
        "charge": 81.3,
        "discharge": 71.8
      },
      "anio": {
        "generation": 1400.2,
        "consumption": 3115.1,
        "grid": 1.2,
        "purchase": 1766.6,
        "charge": 559.0,
        "discharge": 508.5
      },
      "alertas3d": 0,
      "alertaPrincipal": ""
    },
    {
      "id": 63525,
      "nombre": "Gonzalo Estevez",
      "kwp": 6.7,
      "tipo": "BATTERY_BACKUP",
      "estado": "NORMAL",
      "potenciaActual": 328.0,
      "consumoActual": 584.0,
      "bateriaSOC": 40.0,
      "dia": {
        "generation": 2.6,
        "consumption": 8.3,
        "grid": 0.0,
        "purchase": 5.8,
        "charge": 0.6,
        "discharge": 0.5
      },
      "mes": {
        "generation": 117.5,
        "consumption": 427.0,
        "grid": 0.0,
        "purchase": 314.4,
        "charge": 54.1,
        "discharge": 49.2
      },
      "anio": {
        "generation": 1508.7,
        "consumption": 3383.0,
        "grid": 0.0,
        "purchase": 1915.5,
        "charge": 634.0,
        "discharge": 592.8
      },
      "alertas3d": 0,
      "alertaPrincipal": ""
    },
    {
      "id": 94988,
      "nombre": "Victor - Altamira",
      "kwp": 4.0,
      "tipo": "BATTERY_BACKUP",
      "estado": "NORMAL",
      "potenciaActual": 212.0,
      "consumoActual": 162.0,
      "bateriaSOC": 100.0,
      "dia": {
        "generation": 1.3,
        "consumption": 2.8,
        "grid": 0.0,
        "purchase": 1.6,
        "charge": 0.1,
        "discharge": 0.0
      },
      "mes": {
        "generation": 38.0,
        "consumption": 129.2,
        "grid": 0.0,
        "purchase": 93.5,
        "charge": 2.3,
        "discharge": 0.0
      },
      "anio": {
        "generation": 417.2,
        "consumption": 1031.0,
        "grid": 0.0,
        "purchase": 657.4,
        "charge": 44.0,
        "discharge": 0.4
      },
      "alertas3d": 0,
      "alertaPrincipal": ""
    },
    {
      "id": 95147,
      "nombre": "Victor - Farmacia",
      "kwp": 3.78,
      "tipo": "EXCESS",
      "estado": "NORMAL",
      "potenciaActual": 261.0,
      "consumoActual": null,
      "bateriaSOC": null,
      "dia": {
        "generation": 4.0,
        "consumption": 0.0,
        "grid": 0.0,
        "purchase": 0.0,
        "charge": 0.0,
        "discharge": 0.0
      },
      "mes": {
        "generation": 167.9,
        "consumption": 0.0,
        "grid": 0.0,
        "purchase": 0.0,
        "charge": 0.0,
        "discharge": 0.0
      },
      "anio": {
        "generation": 2784.4,
        "consumption": 0.0,
        "grid": 0.0,
        "purchase": 0.0,
        "charge": 0.0,
        "discharge": 0.0
      },
      "alertas3d": 0,
      "alertaPrincipal": ""
    },
    {
      "id": 119820,
      "nombre": "Jose Open Door",
      "kwp": 5.8,
      "tipo": "BATTERY_BACKUP",
      "estado": "NORMAL",
      "potenciaActual": 518.0,
      "consumoActual": 368.0,
      "bateriaSOC": 48.0,
      "dia": {
        "generation": 3.9,
        "consumption": 13.0,
        "grid": 0.0,
        "purchase": 9.8,
        "charge": 0.9,
        "discharge": 0.2
      },
      "mes": {
        "generation": 122.9,
        "consumption": 479.0,
        "grid": 0.0,
        "purchase": 359.9,
        "charge": 49.9,
        "discharge": 46.1
      },
      "anio": {
        "generation": 2101.9,
        "consumption": 4739.8,
        "grid": 8.3,
        "purchase": 2679.2,
        "charge": 774.1,
        "discharge": 734.5
      },
      "alertas3d": 0,
      "alertaPrincipal": ""
    },
    {
      "id": 121126,
      "nombre": "Marianela Lujan",
      "kwp": 4.68,
      "tipo": "BATTERY_BACKUP",
      "estado": "NORMAL",
      "potenciaActual": 242.0,
      "consumoActual": 831.0,
      "bateriaSOC": 36.0,
      "dia": {
        "generation": 3.5,
        "consumption": 8.4,
        "grid": 0.0,
        "purchase": 4.9,
        "charge": 0.7,
        "discharge": 0.7
      },
      "mes": {
        "generation": 168.5,
        "consumption": 314.2,
        "grid": 0.0,
        "purchase": 144.6,
        "charge": 78.4,
        "discharge": 79.5
      },
      "anio": {
        "generation": 1758.7,
        "consumption": 3196.9,
        "grid": 0.0,
        "purchase": 1440.7,
        "charge": 555.1,
        "discharge": 552.6
      },
      "alertas3d": 0,
      "alertaPrincipal": ""
    },
    {
      "id": 127142,
      "nombre": "Marco - Uribelarrea",
      "kwp": 7.0,
      "tipo": "BATTERY_BACKUP",
      "estado": "NORMAL",
      "potenciaActual": 210.0,
      "consumoActual": 155.0,
      "bateriaSOC": 99.0,
      "dia": {
        "generation": 5.4,
        "consumption": 3.3,
        "grid": 0.0,
        "purchase": 0.2,
        "charge": 3.8,
        "discharge": 3.7
      },
      "mes": {
        "generation": 119.5,
        "consumption": 227.6,
        "grid": 0.0,
        "purchase": 186.6,
        "charge": 69.7,
        "discharge": 56.2
      },
      "anio": {
        "generation": 1280.3,
        "consumption": 1922.4,
        "grid": 0.3,
        "purchase": 1294.2,
        "charge": 491.3,
        "discharge": 413.3
      },
      "alertas3d": 0,
      "alertaPrincipal": ""
    },
    {
      "id": 151412,
      "nombre": "Ashley Manzanares",
      "kwp": 21.0,
      "tipo": "BATTERY_BACKUP",
      "estado": "NORMAL",
      "potenciaActual": 600.0,
      "consumoActual": 172.0,
      "bateriaSOC": 100.0,
      "dia": {
        "generation": 10.8,
        "consumption": 4.7,
        "grid": 0.0,
        "purchase": 0.0,
        "charge": 6.1,
        "discharge": 3.8
      },
      "mes": {
        "generation": 218.5,
        "consumption": 112.0,
        "grid": 0.0,
        "purchase": 0.0,
        "charge": 107.0,
        "discharge": 111.2
      },
      "anio": {
        "generation": 1046.1,
        "consumption": 551.5,
        "grid": 0.0,
        "purchase": 0.0,
        "charge": 556.0,
        "discharge": 575.6
      },
      "alertas3d": 0,
      "alertaPrincipal": ""
    },
    {
      "id": 155994,
      "nombre": "Brenda Villa Crespo",
      "kwp": 5.0,
      "tipo": "BATTERY_BACKUP",
      "estado": "NORMAL",
      "potenciaActual": 1132.0,
      "consumoActual": 1475.0,
      "bateriaSOC": 49.0,
      "dia": {
        "generation": 7.9,
        "consumption": 32.9,
        "grid": 0.0,
        "purchase": 26.0,
        "charge": 1.0,
        "discharge": 0.0
      },
      "mes": {
        "generation": 196.0,
        "consumption": 713.7,
        "grid": 0.0,
        "purchase": 524.8,
        "charge": 42.6,
        "discharge": 35.5
      },
      "anio": {
        "generation": 1218.2,
        "consumption": 4111.0,
        "grid": 0.0,
        "purchase": 2954.4,
        "charge": 331.6,
        "discharge": 270.0
      },
      "alertas3d": 0,
      "alertaPrincipal": ""
    },
    {
      "id": 180099,
      "nombre": "Las Lechuzas 105 - Gabriela",
      "kwp": 4.7,
      "tipo": "BATTERY_BACKUP",
      "estado": "NORMAL",
      "potenciaActual": 310.0,
      "consumoActual": 410.0,
      "bateriaSOC": 99.0,
      "dia": {
        "generation": 4.3,
        "consumption": 10.5,
        "grid": 0.0,
        "purchase": 11.4,
        "charge": 3.3,
        "discharge": 0.5
      },
      "mes": {
        "generation": 127.3,
        "consumption": 287.8,
        "grid": 0.0,
        "purchase": 235.7,
        "charge": 67.7,
        "discharge": 63.8
      },
      "anio": {
        "generation": 424.9,
        "consumption": 901.6,
        "grid": 0.0,
        "purchase": 706.3,
        "charge": 203.3,
        "discharge": 192.9
      },
      "alertas3d": 0,
      "alertaPrincipal": ""
    },
    {
      "id": 181096,
      "nombre": "Fernando Mulet (Lima)",
      "kwp": 9.4,
      "tipo": "BATTERY_BACKUP",
      "estado": "NORMAL",
      "potenciaActual": 380.0,
      "consumoActual": 143.0,
      "bateriaSOC": 99.0,
      "dia": {
        "generation": 5.9,
        "consumption": 3.9,
        "grid": 0.0,
        "purchase": 2.5,
        "charge": 6.0,
        "discharge": 3.9
      },
      "mes": {
        "generation": 202.7,
        "consumption": 339.6,
        "grid": 0.4,
        "purchase": 224.4,
        "charge": 140.0,
        "discharge": 126.1
      },
      "anio": {
        "generation": 467.1,
        "consumption": 965.0,
        "grid": 0.5,
        "purchase": 758.8,
        "charge": 297.7,
        "discharge": 263.5
      },
      "alertas3d": 0,
      "alertaPrincipal": ""
    },
    {
      "id": 181243,
      "nombre": "Leonardo Panzuto (Los Talas)",
      "kwp": 7.0,
      "tipo": "BATTERY_BACKUP",
      "estado": "NORMAL",
      "potenciaActual": 256.0,
      "consumoActual": 292.0,
      "bateriaSOC": 71.0,
      "dia": {
        "generation": 6.2,
        "consumption": 7.5,
        "grid": 0.0,
        "purchase": 4.6,
        "charge": 3.6,
        "discharge": 0.3
      },
      "mes": {
        "generation": 139.7,
        "consumption": 262.2,
        "grid": 0.0,
        "purchase": 143.7,
        "charge": 87.4,
        "discharge": 66.2
      },
      "anio": {
        "generation": 400.8,
        "consumption": 725.9,
        "grid": 0.0,
        "purchase": 384.9,
        "charge": 251.9,
        "discharge": 192.1
      },
      "alertas3d": 0,
      "alertaPrincipal": ""
    },
    {
      "id": 181249,
      "nombre": "Angel Corvalan (Barrio San Lucas)",
      "kwp": 7.0,
      "tipo": "BATTERY_BACKUP",
      "estado": "NORMAL",
      "potenciaActual": 189.0,
      "consumoActual": 1544.0,
      "bateriaSOC": 84.0,
      "dia": {
        "generation": 7.6,
        "consumption": 21.5,
        "grid": 0.0,
        "purchase": 14.4,
        "charge": 0.7,
        "discharge": 0.2
      },
      "mes": {
        "generation": 121.9,
        "consumption": 665.6,
        "grid": 0.0,
        "purchase": 550.4,
        "charge": 28.2,
        "discharge": 21.5
      },
      "anio": {
        "generation": 310.3,
        "consumption": 1460.9,
        "grid": 0.0,
        "purchase": 1180.2,
        "charge": 78.5,
        "discharge": 48.9
      },
      "alertas3d": 2,
      "alertaPrincipal": "F56DC VoltLow Fault"
    },
    {
      "id": 187728,
      "nombre": "Matias Borello (Costa)",
      "kwp": 9.4,
      "tipo": "BATTERY_BACKUP",
      "estado": "NORMAL",
      "potenciaActual": 600.0,
      "consumoActual": 526.0,
      "bateriaSOC": 100.0,
      "dia": {
        "generation": 12.6,
        "consumption": 10.4,
        "grid": 1.6,
        "purchase": 7.4,
        "charge": 6.5,
        "discharge": 0.1
      },
      "mes": {
        "generation": 213.1,
        "consumption": 433.7,
        "grid": 28.4,
        "purchase": 314.9,
        "charge": 120.8,
        "discharge": 105.1
      },
      "anio": {
        "generation": 422.7,
        "consumption": 772.5,
        "grid": 49.8,
        "purchase": 522.2,
        "charge": 241.8,
        "discharge": 217.5
      },
      "alertas3d": 0,
      "alertaPrincipal": ""
    },
    {
      "id": 187729,
      "nombre": "Brenda Borello (Costa)",
      "kwp": 4.7,
      "tipo": "BATTERY_BACKUP",
      "estado": "NORMAL",
      "potenciaActual": 378.0,
      "consumoActual": 21.0,
      "bateriaSOC": null,
      "dia": {
        "generation": 6.1,
        "consumption": 0.7,
        "grid": 5.4,
        "purchase": 0.0,
        "charge": 0.0,
        "discharge": 0.0
      },
      "mes": {
        "generation": 86.6,
        "consumption": 14.8,
        "grid": 74.7,
        "purchase": 2.9,
        "charge": 0.0,
        "discharge": 0.0
      },
      "anio": {
        "generation": 131.3,
        "consumption": 111.7,
        "grid": 91.8,
        "purchase": 72.2,
        "charge": 0.0,
        "discharge": 0.0
      },
      "alertas3d": 0,
      "alertaPrincipal": ""
    },
    {
      "id": 192618,
      "nombre": "Julieta Veneziano (El Cazador)",
      "kwp": 4.7,
      "tipo": "BATTERY_BACKUP",
      "estado": "NORMAL",
      "potenciaActual": 136.0,
      "consumoActual": 440.0,
      "bateriaSOC": 48.0,
      "dia": {
        "generation": 2.0,
        "consumption": 13.0,
        "grid": 0.0,
        "purchase": 11.2,
        "charge": 0.4,
        "discharge": 0.2
      },
      "mes": {
        "generation": 109.0,
        "consumption": 386.8,
        "grid": 0.0,
        "purchase": 284.8,
        "charge": 36.5,
        "discharge": 29.5
      },
      "anio": {
        "generation": 139.4,
        "consumption": 523.9,
        "grid": 0.0,
        "purchase": 401.1,
        "charge": 46.7,
        "discharge": 30.1
      },
      "alertas3d": 0,
      "alertaPrincipal": ""
    }
  ]
}